{
  "version": "5",
  "dialect": "pg",
  "id": "a99e8ffe-5d8b-4a7a-a199-276f38fa79f5",
  "prevId": "00000000-0000-0000-0000-000000000000",
  "tables": {
    "blog": {
      "name": "blog",
      "schema": "",
      "columns": {
        "id": {
          "name": "id",
          "type": "serial",
          "primaryKey": false,
          "notNull": true
        }
      },
      "indexes": {},
      "foreignKeys": {},
      "compositePrimaryKeys": {},
      "uniqueConstraints": {}
    }
  },
  "enums": {},
  "schemas": {},
  "_meta": {
    "schemas": {},
    "tables": {},
    "columns": {}
  }
}